fluxpipe/__init__.py
fluxpipe/handler (REVISE).py
fluxpipe/main.py
fluxpipe/version.py
fluxpipe/_core/__init__.py
fluxpipe/_core/addons.py
fluxpipe/_core/commons.py
fluxpipe/_core/constants.py
fluxpipe/_core/meteorologicalfunctions.py
fluxpipe/_core/micrometeorology.py
fluxpipe/_core/read_data.py
fluxpipe/_core/setup_file.py
fluxpipe/_core/units (REVISE).py
fluxpipe/_core/utils.py
fluxpipe/compatibility/__init__.py
fluxpipe/compatibility/EddyPro/__init__.py
fluxpipe/compatibility/EddyPro/setup.py
fluxpipe/compatibility/OneFlux/__init__.py
fluxpipe/compatibility/OneFlux/config.py
fluxpipe/compatibility/PyFluxPro/__init__.py
fluxpipe/compatibility/PyFluxPro/config.py
fluxpipe/corrections/__init__.py
fluxpipe/corrections/axis_rotation/__init__.py
fluxpipe/corrections/axis_rotation/wilczak_et_al_2001.py
fluxpipe/corrections/despiking/__init__.py
fluxpipe/corrections/despiking/mauder_et_al_2013.py
fluxpipe/corrections/misc/__init__.py
fluxpipe/corrections/spectral/__init__.py
fluxpipe/corrections/spectral/experimental_spectra.py
fluxpipe/corrections/time_lag/__init__.py
fluxpipe/corrections/time_lag/fixed.py
fluxpipe/corrections/time_lag/maximisation.py
fluxpipe/corrections/time_lag/theoretical.py
fluxpipe/external/__init__.py
fluxpipe/external/load_era5.py
fluxpipe/footprint/__init__.py
fluxpipe/footprint/kljun_et_al_2015.py
fluxpipe/gapfilling/__init__.py
fluxpipe/gapfilling/pfp_gfMDS.py
fluxpipe/gapfilling/pyfluxpro.py
fluxpipe/gapfilling/reichstein_et_al_2005_PY.py
fluxpipe/gapfilling/vekuri_et_al_2023_PY.py
fluxpipe/gapfilling/xr_interpolation.py
fluxpipe/io/__init__.py
fluxpipe/io/export/__init__.py
fluxpipe/io/import_/__init__.py
fluxpipe/partitioning/__init__.py
fluxpipe/process/__init__.py
fluxpipe/process/conventional_covariance.py
fluxpipe/qaqc/__init__.py
fluxpipe/qaqc/stationarity.py
fluxpipe/qaqc/turbulence.py
oneflux_preproc/__init__.py
oneflux_preproc/main.py
oneflux_preproc/ui.py
oneflux_preproc/version.py
oneflux_preproc/_core/__init__.py
oneflux_preproc-0.0.0.0.1.dist-info/METADATA
oneflux_preproc-0.0.0.0.1.dist-info/WHEEL
oneflux_preproc-0.0.0.0.1.dist-info/top_level.txt
oneflux_preproc-0.0.0.0.1.dist-info/RECORD
